strsplit/__init__.py
strsplit-1.0.0.dist-info/LICENSE
strsplit-1.0.0.dist-info/METADATA
strsplit-1.0.0.dist-info/WHEEL
strsplit-1.0.0.dist-info/top_level.txt
strsplit-1.0.0.dist-info/RECORD
