Metadata-Version: 2.1
Name: strsplit
Version: 1.0.0
Summary: Easy splitting of strings
Home-page: https://github.com/not-nef/strsplit
Author: not-nef
License: MIT
Keywords: strsplit
Platform: UNKNOWN
License-File: LICENSE
